main/__init__.py
vuln_pillow_wrapper-0.0.1.dist-info/LICENSE
vuln_pillow_wrapper-0.0.1.dist-info/METADATA
vuln_pillow_wrapper-0.0.1.dist-info/WHEEL
vuln_pillow_wrapper-0.0.1.dist-info/top_level.txt
vuln_pillow_wrapper-0.0.1.dist-info/RECORD
